gstools/__init__.py
gstools/_version.py
gstools/config.py
gstools/covmodel/__init__.py
gstools/covmodel/base.py
gstools/covmodel/fit.py
gstools/covmodel/models.py
gstools/covmodel/plot.py
gstools/covmodel/sum_tools.py
gstools/covmodel/tools.py
gstools/covmodel/tpl_models.py
gstools/field/__init__.py
gstools/field/base.py
gstools/field/cond_srf.py
gstools/field/generator.py
gstools/field/pgs.py
gstools/field/plot.py
gstools/field/srf.py
gstools/field/tools.py
gstools/field/upscaling.py
gstools/krige/__init__.py
gstools/krige/base.py
gstools/krige/methods.py
gstools/krige/tools.py
gstools/normalizer/__init__.py
gstools/normalizer/base.py
gstools/normalizer/methods.py
gstools/normalizer/tools.py
gstools/random/__init__.py
gstools/random/rng.py
gstools/random/tools.py
gstools/tools/__init__.py
gstools/tools/export.py
gstools/tools/geometric.py
gstools/tools/misc.py
gstools/tools/special.py
gstools/transform/__init__.py
gstools/transform/array.py
gstools/transform/field.py
gstools/variogram/__init__.py
gstools/variogram/binning.py
gstools/variogram/variogram.py
gstools-1.7.0.dist-info/METADATA
gstools-1.7.0.dist-info/WHEEL
gstools-1.7.0.dist-info/licenses/AUTHORS.md
gstools-1.7.0.dist-info/licenses/LICENSE
gstools-1.7.0.dist-info/RECORD
