Metadata-Version: 2.4
Name: gstools
Version: 1.7.0
Summary: GSTools: A geostatistical toolbox.
Project-URL: Changelog, https://github.com/GeoStat-Framework/GSTools/blob/main/CHANGELOG.md
Project-URL: Conda-Forge, https://anaconda.org/conda-forge/gstools
Project-URL: Documentation, https://gstools.readthedocs.io
Project-URL: Homepage, https://geostat-framework.org/#gstools
Project-URL: Source, https://github.com/GeoStat-Framework/GSTools
Project-URL: Tracker, https://github.com/GeoStat-Framework/GSTools/issues
Author-email: "Sebastian Müller, Lennart Schüler" <info@geostat-framework.org>
License-Expression: LGPL-3.0
License-File: AUTHORS.md
License-File: LICENSE
Classifier: Development Status :: 5 - Production/Stable
Classifier: Intended Audience :: Developers
Classifier: Intended Audience :: Education
Classifier: Intended Audience :: End Users/Desktop
Classifier: Intended Audience :: Science/Research
Classifier: License :: OSI Approved :: GNU Lesser General Public License v3 (LGPLv3)
Classifier: Natural Language :: English
Classifier: Operating System :: MacOS
Classifier: Operating System :: Microsoft
Classifier: Operating System :: Unix
Classifier: Programming Language :: Python
Classifier: Programming Language :: Python :: 3
Classifier: Programming Language :: Python :: 3 :: Only
Classifier: Programming Language :: Python :: 3.8
Classifier: Programming Language :: Python :: 3.9
Classifier: Programming Language :: Python :: 3.10
Classifier: Programming Language :: Python :: 3.11
Classifier: Programming Language :: Python :: 3.12
Classifier: Programming Language :: Python :: 3.13
Classifier: Topic :: Scientific/Engineering
Classifier: Topic :: Scientific/Engineering :: GIS
Classifier: Topic :: Scientific/Engineering :: Hydrology
Classifier: Topic :: Scientific/Engineering :: Mathematics
Classifier: Topic :: Scientific/Engineering :: Physics
Classifier: Topic :: Utilities
Requires-Python: >=3.8
Requires-Dist: emcee>=3.0.0
Requires-Dist: gstools-cython<2,>=1
Requires-Dist: hankel>=1.0.0
Requires-Dist: meshio>=5.1.0
Requires-Dist: numpy>=1.20.0
Requires-Dist: pyevtk>=1.1.1
Requires-Dist: scipy>=1.1.0
Provides-Extra: doc
Requires-Dist: matplotlib>=3.7; extra == 'doc'
Requires-Dist: meshzoo>=0.7; extra == 'doc'
Requires-Dist: myst-parser; extra == 'doc'
Requires-Dist: numpydoc>=1.1; extra == 'doc'
Requires-Dist: pykrige<2,>=1.5; extra == 'doc'
Requires-Dist: pyvista>=0.40; extra == 'doc'
Requires-Dist: sphinx-gallery>=0.8; extra == 'doc'
Requires-Dist: sphinx-rtd-theme>=3; extra == 'doc'
Requires-Dist: sphinx>=7; extra == 'doc'
Requires-Dist: sphinxcontrib-youtube>=1.1; extra == 'doc'
Provides-Extra: lint
Requires-Dist: black>=24; extra == 'lint'
Requires-Dist: isort[colors]; extra == 'lint'
Requires-Dist: pylint; extra == 'lint'
Provides-Extra: plotting
Requires-Dist: matplotlib>=3.7; extra == 'plotting'
Requires-Dist: pyvista>=0.40; extra == 'plotting'
Provides-Extra: rust
Requires-Dist: gstools-core>=1.0.0; extra == 'rust'
Provides-Extra: test
Requires-Dist: pytest-cov>=3; extra == 'test'
